localgenius/__init__.py
localgenius/agents/__init__.py
localgenius/agents/base.py
localgenius/agents/models.py
localgenius/agents/orchestrator.py
localgenius/agents/planner.py
localgenius/agents/registry.py
localgenius/agents/reporter.py
localgenius/agents/executors/__init__.py
localgenius/agents/executors/rag.py
localgenius/agents/executors/search.py
localgenius/cli/__init__.py
localgenius/cli/main.py
localgenius/cli/onboarding.py
localgenius/core/__init__.py
localgenius/core/config.py
localgenius/core/database.py
localgenius/core/embeddings.py
localgenius/core/rag.py
localgenius/mcp/__init__.py
localgenius/mcp/fastmcp_server.py
localgenius/utils/__init__.py
localgenius/utils/document_converter.py
localgenius/utils/indexer.py
localgenius/utils/streaming.py
localgenius/web/__init__.py
localgenius/web/server.py
localgenius-0.10.0.dist-info/licenses/LICENSE
localgenius-0.10.0.dist-info/METADATA
localgenius-0.10.0.dist-info/WHEEL
localgenius-0.10.0.dist-info/entry_points.txt
localgenius-0.10.0.dist-info/top_level.txt
localgenius-0.10.0.dist-info/RECORD
