Metadata-Version: 2.4
Name: localgenius
Version: 0.10.0
Summary: A personal MCP server that acts as a RAG source for your LLM
Author: Marco Kotrotsos
License-Expression: MIT
Project-URL: Homepage, https://github.com/marcokotrotsos/localgenius
Project-URL: Repository, https://github.com/marcokotrotsos/localgenius
Keywords: mcp,rag,llm,claude,openai,vector-search,embeddings
Classifier: Development Status :: 3 - Alpha
Classifier: Intended Audience :: Developers
Classifier: Topic :: Software Development :: Libraries :: Python Modules
Classifier: Programming Language :: Python :: 3
Classifier: Programming Language :: Python :: 3.8
Classifier: Programming Language :: Python :: 3.9
Classifier: Programming Language :: Python :: 3.10
Classifier: Programming Language :: Python :: 3.11
Classifier: Programming Language :: Python :: 3.12
Requires-Python: >=3.8
License-File: LICENSE
Requires-Dist: fastmcp>=0.2.0
Requires-Dist: openai>=1.0.0
Requires-Dist: faiss-cpu>=1.7.4
Requires-Dist: pydantic>=2.0.0
Requires-Dist: pydantic-settings>=2.0.0
Requires-Dist: click>=8.1.0
Requires-Dist: rich>=13.0.0
Requires-Dist: python-dotenv>=1.0.0
Requires-Dist: aiofiles>=23.0.0
Requires-Dist: aiosqlite>=0.19.0
Requires-Dist: aiohttp>=3.9.0
Requires-Dist: aiohttp-cors>=0.7.0
Requires-Dist: numpy>=1.24.0
Requires-Dist: PyYAML>=6.0.0
Provides-Extra: documents
Requires-Dist: marker-pdf>=0.2.0; extra == "documents"
Requires-Dist: pypdf>=3.0.0; extra == "documents"
Requires-Dist: python-docx>=1.0.0; extra == "documents"
Dynamic: license-file
